aspyx_service/__init__.py
aspyx_service/authorization.py
aspyx_service/channels.py
aspyx_service/healthcheck.py
aspyx_service/protobuf.py
aspyx_service/registries.py
aspyx_service/restchannel.py
aspyx_service/server.py
aspyx_service/service.py
aspyx_service/session.py
aspyx_service/generator/__init__.py
aspyx_service/generator/json_schema_generator.py
aspyx_service/generator/openapi_generator.py
aspyx_service-0.11.6.dist-info/METADATA
aspyx_service-0.11.6.dist-info/WHEEL
aspyx_service-0.11.6.dist-info/licenses/LICENSE
aspyx_service-0.11.6.dist-info/RECORD
