Metadata-Version: 2.4
Name: aspyx_service
Version: 0.11.6
Summary: Aspyx Service framework
Author-email: Andreas Ernst <andreas.ernst7@gmail.com>
License: MIT License
License-File: LICENSE
Requires-Python: >=3.9
Requires-Dist: aspyx>=1.9.4
Requires-Dist: fastapi~=0.115.13
Requires-Dist: httpx~=0.28.1
Requires-Dist: msgpack~=1.1.1
Requires-Dist: protobuf~=5.29.4
Requires-Dist: python-consul2~=0.1.5
Requires-Dist: uvicorn[standard]
